fitseq/evo_simulator.py
fitseq/fitseq.py
fitseq-1.5.0.data/scripts/evo_simulator.py
fitseq-1.5.0.data/scripts/fitseq.py
fitseq-1.5.0.dist-info/LICENSE
fitseq-1.5.0.dist-info/METADATA
fitseq-1.5.0.dist-info/WHEEL
fitseq-1.5.0.dist-info/top_level.txt
fitseq-1.5.0.dist-info/RECORD
