Metadata-Version: 2.1
Name: fitseq
Version: 1.5.0
Summary: A utility for fitting lineage fitnesses within a pooled competition experiment, achieved by iteratively optimizing models of individual and population-average lineage fitness.
Home-page: https://github.com/darachm/fitseq
Author: Fangfei Li, Darach Miller
License: MIT
Platform: UNKNOWN
Classifier: Programming Language :: Python :: 3
Classifier: License :: OSI Approved :: MIT License
Requires-Python: >=3.6
License-File: LICENSE
Requires-Dist: numpy (>=1.17.3)
Requires-Dist: pandas (>=0.25.3)
Requires-Dist: scipy (>=1.3.1)
Requires-Dist: tqdm
